CHANGES.rst
CONTRIBUTORS.rst
MANIFEST.in
README.rst
VERSION
pyproject.toml
setup.cfg
setup.py
docs/LICENSE.GPL
docs/LICENSE.rst
src/collective/__init__.py
src/collective.metadataversion.egg-info/PKG-INFO
src/collective.metadataversion.egg-info/SOURCES.txt
src/collective.metadataversion.egg-info/dependency_links.txt
src/collective.metadataversion.egg-info/entry_points.txt
src/collective.metadataversion.egg-info/namespace_packages.txt
src/collective.metadataversion.egg-info/not-zip-safe
src/collective.metadataversion.egg-info/requires.txt
src/collective.metadataversion.egg-info/top_level.txt
src/collective/metadataversion/__init__.py
src/collective/metadataversion/_i18n.py
src/collective/metadataversion/catalog.py
src/collective/metadataversion/config.py
src/collective/metadataversion/configure.zcml
src/collective/metadataversion/decorator.py
src/collective/metadataversion/exceptions.py
src/collective/metadataversion/interfaces.py
src/collective/metadataversion/profiles.zcml
src/collective/metadataversion/setuphandlers.py
src/collective/metadataversion/utils.py
src/collective/metadataversion/Extensions/install.py
src/collective/metadataversion/locales/collective.metadataversion.pot
src/collective/metadataversion/locales/de/LC_MESSAGES/collective.metadataversion.mo
src/collective/metadataversion/locales/de/LC_MESSAGES/collective.metadataversion.po
src/collective/metadataversion/locales/en/LC_MESSAGES/collective.metadataversion.mo
src/collective/metadataversion/locales/en/LC_MESSAGES/collective.metadataversion.po
src/collective/metadataversion/profiles/default/catalog.xml
src/collective/metadataversion/profiles/default/collective.metadataversion-default.marker
src/collective/metadataversion/profiles/default/metadata.xml
src/collective/metadataversion/profiles/default/registry.xml
src/collective/metadataversion/profiles/uninstall/registry.xml