Metadata-Version: 2.1
Name: collective.metadataversion
Version: 0.2.2
Summary: Simple metadata evolution tracking
Home-page: UNKNOWN
Author: Tobias Herp
Author-email: tobias.herp@visaplan.com
License: GPL version 2
Project-URL: Source, https://github.com/collective/metadataversion
Project-URL: Documentation, https://pypi.org/project/collective.metadataversion
Project-URL: Tracker, https://github.com/collective/metadataversion/issues
Platform: UNKNOWN
Classifier: Environment :: Web Environment
Classifier: Framework :: Plone
Classifier: Framework :: Plone :: 4.3
Classifier: Framework :: Zope2
Classifier: Programming Language :: Python
Classifier: Programming Language :: Python :: 2.7
Classifier: Programming Language :: Python :: 3
Classifier: Intended Audience :: Developers
Classifier: Operating System :: OS Independent
Classifier: License :: OSI Approved :: GNU General Public License v2 (GPLv2)
